poetry_gerencia/__init__.py
poetry_gerencia-0.1.0.dist-info/METADATA
poetry_gerencia-0.1.0.dist-info/WHEEL
poetry_gerencia-0.1.0.dist-info/RECORD
