Metadata-Version: 2.1
Name: poetry-gerencia
Version: 0.1.0
Summary: 
Author: Eduardo Gurgel
Author-email: 51385738+EduardoGurgel@users.noreply.github.com
Requires-Python: >=3.8,<4.0
Classifier: Programming Language :: Python :: 3
Classifier: Programming Language :: Python :: 3.8
Classifier: Programming Language :: Python :: 3.9
Classifier: Programming Language :: Python :: 3.10
Classifier: Programming Language :: Python :: 3.11
Requires-Dist: pyglet (>=2.0.3,<3.0.0)
